django_typeform/__init__.py
django_typeform/apps.py
django_typeform/forms.py
django_typeform/responses.py
django_typeform/views.py
django_typeform/templates/django_typeform/typeform.html
django_typeform/templates/django_typeform/typeform_embed.html
django_typeform/templatetags/__init__.py
django_typeform/templatetags/django_typeform.py
django_typeform-0.2.0.dist-info/DESCRIPTION.rst
django_typeform-0.2.0.dist-info/METADATA
django_typeform-0.2.0.dist-info/RECORD
django_typeform-0.2.0.dist-info/WHEEL
django_typeform-0.2.0.dist-info/metadata.json
django_typeform-0.2.0.dist-info/top_level.txt
