Metadata-Version: 2.0
Name: django-typeform
Version: 0.2.0
Summary: A Typeform integration for Django
Home-page: https://github.com/redapesolutions/django-typeform
Author: Jafnee Jesmee
Author-email: jafnee@redapesolutions.com
License: MIT
Keywords: django-typeform
Platform: UNKNOWN
Classifier: Development Status :: 3 - Alpha
Classifier: Framework :: Django
Classifier: Framework :: Django :: 1.11
Classifier: Framework :: Django :: 2.0
Classifier: Framework :: Django :: 2.1
Classifier: Framework :: Django :: 2.2
Classifier: Intended Audience :: Developers
Classifier: License :: OSI Approved :: MIT License
Classifier: Natural Language :: English
Classifier: Programming Language :: Python :: 3
Classifier: Programming Language :: Python :: 3.5
Classifier: Programming Language :: Python :: 3.6
Classifier: Programming Language :: Python :: 3.7
